{
  "hooks": {
    "PostToolUse": [
      {
        "matcher": "Bash",
        "hooks": [
          {
            "type": "command",
            "command": "PYTHONPATH=/home/dkremer/jamb python3 -m jamb reward --stat debugging --amount 1 --xp 2",
            "async": true
          },
          {
            "type": "command",
            "command": "/home/dkremer/jamb/jamb-plugin/hooks/react.sh",
            "async": true
          }
        ]
      },
      {
        "matcher": "Edit",
        "hooks": [
          {
            "type": "command",
            "command": "PYTHONPATH=/home/dkremer/jamb python3 -m jamb reward --stat patience --amount 1 --xp 2",
            "async": true
          }
        ]
      },
      {
        "matcher": "Write",
        "hooks": [
          {
            "type": "command",
            "command": "PYTHONPATH=/home/dkremer/jamb python3 -m jamb reward --stat wisdom --amount 1 --xp 2",
            "async": true
          }
        ]
      },
      {
        "matcher": "Agent",
        "hooks": [
          {
            "type": "command",
            "command": "PYTHONPATH=/home/dkremer/jamb python3 -m jamb reward --stat chaos --amount 1 --xp 2",
            "async": true
          }
        ]
      },
      {
        "matcher": "Grep",
        "hooks": [
          {
            "type": "command",
            "command": "PYTHONPATH=/home/dkremer/jamb python3 -m jamb reward --stat snark --amount 1 --xp 2",
            "async": true
          }
        ]
      },
      {
        "matcher": "Glob",
        "hooks": [
          {
            "type": "command",
            "command": "PYTHONPATH=/home/dkremer/jamb python3 -m jamb reward --stat snark --amount 1 --xp 1",
            "async": true
          }
        ]
      },
      {
        "matcher": "Read",
        "hooks": [
          {
            "type": "command",
            "command": "PYTHONPATH=/home/dkremer/jamb python3 -m jamb reward --stat wisdom --amount 1 --xp 1",
            "async": true
          }
        ]
      }
    ],
    "SessionStart": [
      {
        "hooks": [
          {
            "type": "command",
            "command": "PYTHONPATH=/home/dkremer/jamb python3 -m jamb reward --stat wisdom --amount 0 --xp 5",
            "async": true
          }
        ]
      }
    ],
    "SessionEnd": [
      {
        "hooks": [
          {
            "type": "command",
            "command": "PYTHONPATH=/home/dkremer/jamb python3 -m jamb session-end",
            "async": true
          }
        ]
      }
    ],
    "Stop": [
      {
        "hooks": [
          {
            "type": "command",
            "command": "/home/dkremer/jamb/jamb-plugin/hooks/buddy-comment.sh",
            "async": true
          }
        ]
      }
    ]
  }
}
